[{"Position":0,"Link":"circuitbreaker","Title":"Circuit Breaker","Match":0,"MenuItems":[{"Position":0,"Link":"circuitbreaker/circuitbreaker-hystrix","Title":"Hystrix","Match":0,"MenuItems":[{"Position":0,"Link":"circuitbreaker/circuitbreaker-hystrix#usage","Title":"Usage","Match":0,"MenuItems":null,"IsVisible":true,"IsEnabled":true,"MatchLink":"Prefix"}],"IsVisible":true,"IsEnabled":true,"MatchLink":"Prefix"},{"Position":0,"Link":"circuitbreaker/circuitbreaker-overview","Title":"Overview","Match":0,"MenuItems":null,"IsVisible":true,"IsEnabled":true,"MatchLink":"Prefix"}],"IsVisible":true,"IsEnabled":true,"MatchLink":"All"},{"Position":0,"Link":"configuration","Title":"Application Configuration","Match":0,"MenuItems":[{"Position":0,"Link":"configuration/configuration-cloudfoundryprovider","Title":"Cloudfoundryprovider","Match":0,"MenuItems":[{"Position":0,"Link":"configuration/configuration-cloudfoundryprovider#usage","Title":"Usage","Match":0,"MenuItems":null,"IsVisible":true,"IsEnabled":true,"MatchLink":"Prefix"}],"IsVisible":true,"IsEnabled":true,"MatchLink":"Prefix"},{"Position":0,"Link":"configuration/configuration-configserverprovider","Title":"Configserverprovider","Match":0,"MenuItems":[{"Position":0,"Link":"configuration/configuration-configserverprovider#usage","Title":"Usage","Match":0,"MenuItems":null,"IsVisible":true,"IsEnabled":true,"MatchLink":"Prefix"}],"IsVisible":true,"IsEnabled":true,"MatchLink":"Prefix"},{"Position":0,"Link":"configuration/configuration-hostedextensions","Title":"Hostedextensions","Match":0,"MenuItems":null,"IsVisible":true,"IsEnabled":true,"MatchLink":"Prefix"},{"Position":0,"Link":"configuration/configuration-overview","Title":"Overview","Match":0,"MenuItems":null,"IsVisible":true,"IsEnabled":true,"MatchLink":"Prefix"},{"Position":0,"Link":"configuration/configuration-placeholderprovider","Title":"Placeholderprovider","Match":0,"MenuItems":[{"Position":0,"Link":"configuration/configuration-placeholderprovider#usage","Title":"Usage","Match":0,"MenuItems":null,"IsVisible":true,"IsEnabled":true,"MatchLink":"Prefix"}],"IsVisible":true,"IsEnabled":true,"MatchLink":"Prefix"},{"Position":0,"Link":"configuration/configuration-randomvalueprovider","Title":"Randomvalueprovider","Match":0,"MenuItems":[{"Position":0,"Link":"configuration/configuration-randomvalueprovider#usage","Title":"Usage","Match":0,"MenuItems":null,"IsVisible":true,"IsEnabled":true,"MatchLink":"Prefix"}],"IsVisible":true,"IsEnabled":true,"MatchLink":"Prefix"}],"IsVisible":true,"IsEnabled":true,"MatchLink":"All"},{"Position":0,"Link":"connectors","Title":"Cloud Connectors","Match":0,"MenuItems":[{"Position":0,"Link":"connectors/connectors-microsoftsqlserver","Title":"Microsoftsqlserver","Match":0,"MenuItems":[{"Position":0,"Link":"connectors/connectors-microsoftsqlserver#usage","Title":"Usage","Match":0,"MenuItems":null,"IsVisible":true,"IsEnabled":true,"MatchLink":"Prefix"}],"IsVisible":true,"IsEnabled":true,"MatchLink":"Prefix"},{"Position":0,"Link":"connectors/connectors-mongodb","Title":"Mongodb","Match":0,"MenuItems":null,"IsVisible":true,"IsEnabled":true,"MatchLink":"Prefix"},{"Position":0,"Link":"connectors/connectors-mysql","Title":"Mysql","Match":0,"MenuItems":[{"Position":0,"Link":"connectors/connectors-mysql#usage","Title":"Usage","Match":0,"MenuItems":null,"IsVisible":true,"IsEnabled":true,"MatchLink":"Prefix"}],"IsVisible":true,"IsEnabled":true,"MatchLink":"Prefix"},{"Position":0,"Link":"connectors/connectors-oauth","Title":"Oauth","Match":0,"MenuItems":[{"Position":0,"Link":"connectors/connectors-oauth#usage","Title":"Usage","Match":0,"MenuItems":null,"IsVisible":true,"IsEnabled":true,"MatchLink":"Prefix"}],"IsVisible":true,"IsEnabled":true,"MatchLink":"Prefix"},{"Position":0,"Link":"connectors/connectors-overview","Title":"Overview","Match":0,"MenuItems":null,"IsVisible":true,"IsEnabled":true,"MatchLink":"Prefix"},{"Position":0,"Link":"connectors/connectors-postgresql","Title":"Postgresql","Match":0,"MenuItems":[{"Position":0,"Link":"connectors/connectors-postgresql#usage","Title":"Usage","Match":0,"MenuItems":null,"IsVisible":true,"IsEnabled":true,"MatchLink":"Prefix"}],"IsVisible":true,"IsEnabled":true,"MatchLink":"Prefix"},{"Position":0,"Link":"connectors/connectors-rabbitmq","Title":"Rabbitmq","Match":0,"MenuItems":[{"Position":0,"Link":"connectors/connectors-rabbitmq#usage","Title":"Usage","Match":0,"MenuItems":null,"IsVisible":true,"IsEnabled":true,"MatchLink":"Prefix"}],"IsVisible":true,"IsEnabled":true,"MatchLink":"Prefix"},{"Position":0,"Link":"connectors/connectors-redis","Title":"Redis","Match":0,"MenuItems":[{"Position":0,"Link":"connectors/connectors-redis#usage","Title":"Usage","Match":0,"MenuItems":null,"IsVisible":true,"IsEnabled":true,"MatchLink":"Prefix"}],"IsVisible":true,"IsEnabled":true,"MatchLink":"Prefix"}],"IsVisible":true,"IsEnabled":true,"MatchLink":"All"},{"Position":0,"Link":"discovery","Title":"Service Discovery","Match":0,"MenuItems":[{"Position":0,"Link":"discovery/discovery-discoveringservices","Title":"Discoveringservices","Match":0,"MenuItems":[{"Position":0,"Link":"discovery/discovery-discoveringservices#discovering-services","Title":"Discovering Services","Match":0,"MenuItems":null,"IsVisible":true,"IsEnabled":true,"MatchLink":"Prefix"}],"IsVisible":true,"IsEnabled":true,"MatchLink":"Prefix"},{"Position":0,"Link":"discovery/discovery-enablelogging","Title":"Enablelogging","Match":0,"MenuItems":[{"Position":0,"Link":"discovery/discovery-enablelogging#enable-logging","Title":"Enable Logging","Match":0,"MenuItems":null,"IsVisible":true,"IsEnabled":true,"MatchLink":"Prefix"}],"IsVisible":true,"IsEnabled":true,"MatchLink":"Prefix"},{"Position":0,"Link":"discovery/discovery-hashicorpconsul","Title":"Hashicorpconsul","Match":0,"MenuItems":[{"Position":0,"Link":"discovery/discovery-hashicorpconsul#usage","Title":"Usage","Match":0,"MenuItems":null,"IsVisible":true,"IsEnabled":true,"MatchLink":"Prefix"}],"IsVisible":true,"IsEnabled":true,"MatchLink":"Prefix"},{"Position":0,"Link":"discovery/discovery-initializediscoveryclient","Title":"Initializediscoveryclient","Match":0,"MenuItems":[{"Position":0,"Link":"discovery/discovery-initializediscoveryclient#initialize-discovery-client","Title":"Initialize Discovery Client","Match":0,"MenuItems":null,"IsVisible":true,"IsEnabled":true,"MatchLink":"Prefix"}],"IsVisible":true,"IsEnabled":true,"MatchLink":"Prefix"},{"Position":0,"Link":"discovery/discovery-loadbalancing","Title":"Loadbalancing","Match":0,"MenuItems":[{"Position":0,"Link":"discovery/discovery-loadbalancing#load-balancing","Title":"Load Balancing","Match":0,"MenuItems":null,"IsVisible":true,"IsEnabled":true,"MatchLink":"Prefix"}],"IsVisible":true,"IsEnabled":true,"MatchLink":"Prefix"},{"Position":0,"Link":"discovery/discovery-netflixeureka","Title":"Netflixeureka","Match":0,"MenuItems":[{"Position":0,"Link":"discovery/discovery-netflixeureka#usage","Title":"Usage","Match":0,"MenuItems":null,"IsVisible":true,"IsEnabled":true,"MatchLink":"Prefix"}],"IsVisible":true,"IsEnabled":true,"MatchLink":"Prefix"},{"Position":0,"Link":"discovery/discovery-overview","Title":"Overview","Match":0,"MenuItems":[{"Position":0,"Link":"discovery/discovery-overview#add-nuget-references","Title":"Add NuGet References","Match":0,"MenuItems":null,"IsVisible":true,"IsEnabled":true,"MatchLink":"Prefix"}],"IsVisible":true,"IsEnabled":true,"MatchLink":"Prefix"}],"IsVisible":true,"IsEnabled":true,"MatchLink":"All"},{"Position":0,"Link":"fileshares","Title":"Network File Sharing","Match":0,"MenuItems":[{"Position":0,"Link":"fileshares/fileshares-overview","Title":"Overview","Match":0,"MenuItems":null,"IsVisible":true,"IsEnabled":true,"MatchLink":"Prefix"},{"Position":0,"Link":"fileshares/fileshares-usage","Title":"Usage","Match":0,"MenuItems":[{"Position":0,"Link":"fileshares/fileshares-usage#usage","Title":"Usage","Match":0,"MenuItems":null,"IsVisible":true,"IsEnabled":true,"MatchLink":"Prefix"}],"IsVisible":true,"IsEnabled":true,"MatchLink":"Prefix"}],"IsVisible":true,"IsEnabled":true,"MatchLink":"All"},{"Position":0,"Link":"introduction","Title":"Introduction","Match":0,"MenuItems":[{"Position":0,"Link":"introduction/introduction","Title":"","Match":0,"MenuItems":[{"Position":0,"Link":"introduction/introduction#nuget-feeds","Title":"NuGet Feeds","Match":0,"MenuItems":null,"IsVisible":true,"IsEnabled":true,"MatchLink":"Prefix"},{"Position":0,"Link":"introduction/introduction#quick-starts","Title":"Quick Starts","Match":0,"MenuItems":null,"IsVisible":true,"IsEnabled":true,"MatchLink":"Prefix"}],"IsVisible":true,"IsEnabled":true,"MatchLink":"Prefix"}],"IsVisible":true,"IsEnabled":true,"MatchLink":"All"},{"Position":0,"Link":"logging","Title":"Dynamic Logging","Match":0,"MenuItems":[{"Position":0,"Link":"logging/logging-dynamicloggingprovider","Title":"Dynamicloggingprovider","Match":0,"MenuItems":[{"Position":0,"Link":"logging/logging-dynamicloggingprovider#usage","Title":"Usage","Match":0,"MenuItems":null,"IsVisible":true,"IsEnabled":true,"MatchLink":"Prefix"}],"IsVisible":true,"IsEnabled":true,"MatchLink":"Prefix"},{"Position":0,"Link":"logging/logging-overview","Title":"Overview","Match":0,"MenuItems":null,"IsVisible":true,"IsEnabled":true,"MatchLink":"Prefix"}],"IsVisible":true,"IsEnabled":true,"MatchLink":"All"},{"Position":0,"Link":"management","Title":"Cloud Management","Match":0,"MenuItems":[{"Position":0,"Link":"management/management-common-steps","Title":"CommonSteps","Match":0,"MenuItems":[{"Position":0,"Link":"management/management-common-steps#http-access-asp.net-core","Title":"HTTP Access ASP.NET Core","Match":0,"MenuItems":null,"IsVisible":true,"IsEnabled":true,"MatchLink":"Prefix"},{"Position":0,"Link":"management/management-common-steps#http-access-asp.net-4.x","Title":"HTTP Access ASP.NET 4.x","Match":0,"MenuItems":null,"IsVisible":true,"IsEnabled":true,"MatchLink":"Prefix"},{"Position":0,"Link":"management/management-common-steps#http-access-asp.net-owin","Title":"HTTP Access ASP.NET OWIN","Match":0,"MenuItems":null,"IsVisible":true,"IsEnabled":true,"MatchLink":"Prefix"}],"IsVisible":true,"IsEnabled":true,"MatchLink":"Prefix"},{"Position":0,"Link":"management/management-distributedtracing-exporting","Title":"DistributedtracingExporting","Match":0,"MenuItems":[{"Position":0,"Link":"management/management-distributedtracing-exporting#exporting","Title":"Exporting","Match":0,"MenuItems":null,"IsVisible":true,"IsEnabled":true,"MatchLink":"Prefix"}],"IsVisible":true,"IsEnabled":true,"MatchLink":"Prefix"},{"Position":0,"Link":"management/management-distributedtracing-overview","Title":"DistributedtracingOverview","Match":0,"MenuItems":null,"IsVisible":true,"IsEnabled":true,"MatchLink":"Prefix"},{"Position":0,"Link":"management/management-distributedtracing-usage","Title":"DistributedtracingUsage","Match":0,"MenuItems":[{"Position":0,"Link":"management/management-distributedtracing-usage#usage","Title":"Usage","Match":0,"MenuItems":null,"IsVisible":true,"IsEnabled":true,"MatchLink":"Prefix"}],"IsVisible":true,"IsEnabled":true,"MatchLink":"Prefix"},{"Position":0,"Link":"management/management-endpoint-cloudfoundry","Title":"EndpointCloudfoundry","Match":0,"MenuItems":null,"IsVisible":true,"IsEnabled":true,"MatchLink":"Prefix"},{"Position":0,"Link":"management/management-endpoint-env","Title":"EndpointEnv","Match":0,"MenuItems":null,"IsVisible":true,"IsEnabled":true,"MatchLink":"Prefix"},{"Position":0,"Link":"management/management-endpoint-health","Title":"EndpointHealth","Match":0,"MenuItems":null,"IsVisible":true,"IsEnabled":true,"MatchLink":"Prefix"},{"Position":0,"Link":"management/management-endpoint-heapdump","Title":"EndpointHeapdump","Match":0,"MenuItems":null,"IsVisible":true,"IsEnabled":true,"MatchLink":"Prefix"},{"Position":0,"Link":"management/management-endpoint-hypermedia","Title":"EndpointHypermedia","Match":0,"MenuItems":null,"IsVisible":true,"IsEnabled":true,"MatchLink":"Prefix"},{"Position":0,"Link":"management/management-endpoint-info","Title":"EndpointInfo","Match":0,"MenuItems":null,"IsVisible":true,"IsEnabled":true,"MatchLink":"Prefix"},{"Position":0,"Link":"management/management-endpoint-loggers","Title":"EndpointLoggers","Match":0,"MenuItems":null,"IsVisible":true,"IsEnabled":true,"MatchLink":"Prefix"},{"Position":0,"Link":"management/management-endpoint-mappings","Title":"EndpointMappings","Match":0,"MenuItems":null,"IsVisible":true,"IsEnabled":true,"MatchLink":"Prefix"},{"Position":0,"Link":"management/management-endpoint-metrics","Title":"EndpointMetrics","Match":0,"MenuItems":null,"IsVisible":true,"IsEnabled":true,"MatchLink":"Prefix"},{"Position":0,"Link":"management/management-endpoint-overview","Title":"EndpointOverview","Match":0,"MenuItems":[{"Position":0,"Link":"management/management-endpoint-overview#management-endpoints","Title":"Management Endpoints","Match":0,"MenuItems":null,"IsVisible":true,"IsEnabled":true,"MatchLink":"Prefix"}],"IsVisible":true,"IsEnabled":true,"MatchLink":"Prefix"},{"Position":0,"Link":"management/management-endpoint-refresh","Title":"EndpointRefresh","Match":0,"MenuItems":null,"IsVisible":true,"IsEnabled":true,"MatchLink":"Prefix"},{"Position":0,"Link":"management/management-endpoint-threaddump","Title":"EndpointThreaddump","Match":0,"MenuItems":null,"IsVisible":true,"IsEnabled":true,"MatchLink":"Prefix"},{"Position":0,"Link":"management/management-endpoint-tracing","Title":"EndpointTracing","Match":0,"MenuItems":null,"IsVisible":true,"IsEnabled":true,"MatchLink":"Prefix"},{"Position":0,"Link":"management/management-endpoint-usage","Title":"EndpointUsage","Match":0,"MenuItems":[{"Position":0,"Link":"management/management-endpoint-usage#usage","Title":"Usage","Match":0,"MenuItems":null,"IsVisible":true,"IsEnabled":true,"MatchLink":"Prefix"}],"IsVisible":true,"IsEnabled":true,"MatchLink":"Prefix"},{"Position":0,"Link":"management/management-tasks-overview","Title":"TasksOverview","Match":0,"MenuItems":null,"IsVisible":true,"IsEnabled":true,"MatchLink":"Prefix"},{"Position":0,"Link":"management/management-tasks-usage","Title":"TasksUsage","Match":0,"MenuItems":null,"IsVisible":true,"IsEnabled":true,"MatchLink":"Prefix"}],"IsVisible":true,"IsEnabled":true,"MatchLink":"All"},{"Position":0,"Link":"security","Title":"Security Providers","Match":0,"MenuItems":[{"Position":0,"Link":"security/security-credhubapiclient","Title":"Credhubapiclient","Match":0,"MenuItems":[{"Position":0,"Link":"security/security-credhubapiclient#usage","Title":"Usage","Match":0,"MenuItems":null,"IsVisible":true,"IsEnabled":true,"MatchLink":"Prefix"}],"IsVisible":true,"IsEnabled":true,"MatchLink":"Prefix"},{"Position":0,"Link":"security/security-overview","Title":"Overview","Match":0,"MenuItems":null,"IsVisible":true,"IsEnabled":true,"MatchLink":"Prefix"},{"Position":0,"Link":"security/security-rediskeystorageprovider","Title":"Rediskeystorageprovider","Match":0,"MenuItems":[{"Position":0,"Link":"security/security-rediskeystorageprovider#usage","Title":"Usage","Match":0,"MenuItems":null,"IsVisible":true,"IsEnabled":true,"MatchLink":"Prefix"}],"IsVisible":true,"IsEnabled":true,"MatchLink":"Prefix"},{"Position":0,"Link":"security/security-resourceprotectionusingjwt","Title":"Resourceprotectionusingjwt","Match":0,"MenuItems":[{"Position":0,"Link":"security/security-resourceprotectionusingjwt#usage-in-asp.net-core","Title":"Usage in ASP.NET Core","Match":0,"MenuItems":null,"IsVisible":true,"IsEnabled":true,"MatchLink":"Prefix"},{"Position":0,"Link":"security/security-resourceprotectionusingjwt#usage-in-asp.net-webapi","Title":"Usage in ASP.NET WebAPI","Match":0,"MenuItems":null,"IsVisible":true,"IsEnabled":true,"MatchLink":"Prefix"},{"Position":0,"Link":"security/security-resourceprotectionusingjwt#usage-in-asp.net-wcf","Title":"Usage in ASP.NET WCF","Match":0,"MenuItems":null,"IsVisible":true,"IsEnabled":true,"MatchLink":"Prefix"}],"IsVisible":true,"IsEnabled":true,"MatchLink":"Prefix"},{"Position":0,"Link":"security/security-ssooauth2","Title":"Ssooauth2","Match":0,"MenuItems":[{"Position":0,"Link":"security/security-ssooauth2#usage","Title":"Usage","Match":0,"MenuItems":null,"IsVisible":true,"IsEnabled":true,"MatchLink":"Prefix"}],"IsVisible":true,"IsEnabled":true,"MatchLink":"Prefix"},{"Position":0,"Link":"security/security-ssoopenid","Title":"Ssoopenid","Match":0,"MenuItems":[{"Position":0,"Link":"security/security-ssoopenid#usage","Title":"Usage","Match":0,"MenuItems":null,"IsVisible":true,"IsEnabled":true,"MatchLink":"Prefix"}],"IsVisible":true,"IsEnabled":true,"MatchLink":"Prefix"}],"IsVisible":true,"IsEnabled":true,"MatchLink":"All"}]